transformHealthEventHubModels/__init__.py
transformHealthEventHubModels/insertOne.py
transformHealthEventHubModels/updateOne.py
th_eh_models-0.0.6.dist-info/LICENSE
th_eh_models-0.0.6.dist-info/METADATA
th_eh_models-0.0.6.dist-info/WHEEL
th_eh_models-0.0.6.dist-info/top_level.txt
th_eh_models-0.0.6.dist-info/RECORD
