Metadata-Version: 2.1
Name: th-eh-models
Version: 0.0.6
Summary: Models For TH Event Hub
Author: Sachin Dev
License: UNKNOWN
Platform: UNKNOWN
Classifier: Programming Language :: Python :: 3
Classifier: License :: OSI Approved :: MIT License
Classifier: Operating System :: OS Independent
Requires-Python: >=3.6
License-File: LICENSE
